<?xml version="1.0" encoding="UTF-8"?>
<resources>
    <!-- App Name -->
    <string name="app_name">TISM</string>
    <string name="app_subtitle">ASD рдХреЗ рдмрд╛рд░реЗ рдореЗрдВ рдЬреЛ рдХреБрдЫ рднреА рдЬрд╛рдирдирд╛ рд╣реИ рд╡реЛ рдПрдХ рдХреНрд▓рд┐рдХ рдореЗрдВ</string>
    <string name="app_title">TISM - ASD рдЧрд╛рдЗрдб</string>
    
    <!-- Authentication -->
    <string name="login">рд▓реЙрдЧрд┐рди</string>
    <string name="register">рд░рдЬрд┐рд╕реНрдЯрд░</string>
    <string name="email">рдИрдореЗрд▓</string>
    <string name="password">рдкрд╛рд╕рд╡рд░реНрдб</string>
    <string name="confirm_password">рдкрд╛рд╕рд╡рд░реНрдб рдХреА рдкреБрд╖реНрдЯрд┐ рдХрд░реЗрдВ</string>
    <string name="name">рдирд╛рдо</string>
    <string name="username">рдпреВрдЬрд░рдиреЗрдо</string>
    <string name="forgot_password">рдкрд╛рд╕рд╡рд░реНрдб рднреВрд▓ рдЧрдП</string>
    <string name="login_success">рд▓реЙрдЧрд┐рди рд╕рдлрд▓</string>
    <string name="register_success">рдЦрд╛рддрд╛ рд╕рдлрд▓рддрд╛рдкреВрд░реНрд╡рдХ рдмрдирд╛рдпрд╛ рдЧрдпрд╛</string>
    <string name="logout">рд▓реЙрдЧрдЖрдЙрдЯ</string>
    <string name="logout_confirm">рдХреНрдпрд╛ рдЖрдк рд▓реЙрдЧрдЖрдЙрдЯ рдХрд░рдирд╛ рдЪрд╛рд╣рддреЗ рд╣реИрдВ?</string>
    
    <!-- User Types -->
    <string name="participant">рдкреНрд░рддрд┐рднрд╛рдЧреА</string>
    <string name="participant_desc">рдирд┐рдпрдорд┐рдд TISM рдЙрдкрдпреЛрдЧрдХрд░реНрддрд╛</string>
    <string name="responsible">рдЬрд┐рдореНрдореЗрджрд╛рд░</string>
    <string name="responsible_desc">рдкрд░рд┐рд╡рд╛рд░рдЬрди рдпрд╛ рджреЗрдЦрднрд╛рд▓рдХрд░реНрддрд╛</string>
    <string name="professional">рдкреЗрд╢реЗрд╡рд░</string>
    <string name="professional_desc">рдЪрд┐рдХрд┐рддреНрд╕рдХ, рдбреЙрдХреНрдЯрд░, рд╢рд┐рдХреНрд╖рдХ</string>
    <string name="user_type">рдЙрдкрдпреЛрдЧрдХрд░реНрддрд╛ рдкреНрд░рдХрд╛рд░</string>
    <string name="select_user_type">рдЕрдкрдирд╛ рдкреНрд░рдХрд╛рд░ рдЪреБрдиреЗрдВ</string>
    
    <!-- Profile -->
    <string name="profile">рдкреНрд░реЛрдлрд╛рдЗрд▓</string>
    <string name="edit_profile">рдкреНрд░реЛрдлрд╛рдЗрд▓ рд╕рдВрдкрд╛рджрд┐рдд рдХрд░реЗрдВ</string>
    <string name="edit_name">рдирд╛рдо рд╕рдВрдкрд╛рджрд┐рдд рдХрд░реЗрдВ</string>
    <string name="edit_username">рдпреВрдЬрд░рдиреЗрдо рд╕рдВрдкрд╛рджрд┐рдд рдХрд░реЗрдВ</string>
    <string name="full_name">рдкреВрд░рд╛ рдирд╛рдо</string>
    <string name="account_type">рдЦрд╛рддрд╛ рдкреНрд░рдХрд╛рд░</string>
    <string name="theme">рдереАрдо</string>
    <string name="light_theme">рд╣рд▓реНрдХреА</string>
    <string name="dark_theme">рдЧрд╣рд░реА</string>
    <string name="system_theme">рд╕рд┐рд╕реНрдЯрдо</string>
    <string name="system_theme_desc">рдбрд┐рд╡рд╛рдЗрд╕ рдереАрдо рдХрд╛ рдкрд╛рд▓рди рдХрд░реЗрдВ</string>
    
    <!-- Navigation -->
    <string name="home">рд╣реЛрдо</string>
    <string name="forum">рдлреЛрд░рдо</string>
    <string name="knowledge">рдЬреНрдЮрд╛рди</string>
    <string name="routine">рджрд┐рдирдЪрд░реНрдпрд╛</string>
    <string name="dashboard">рдбреИрд╢рдмреЛрд░реНрдб</string>
    <string name="feed">рдлреАрдб</string>
    <string name="search">рдЦреЛрдЬреЗрдВ</string>
    
    <!-- Home Page -->
    <string name="hello_user">рдирдорд╕реНрддреЗ, %s! ЁЯСЛ</string>
    <string name="explore_content">ASD рдХреЗ рдмрд╛рд░реЗ рдореЗрдВ рд╢реИрдХреНрд╖рд┐рдХ рд╕рд╛рдордЧреНрд░реА рджреЗрдЦреЗрдВ</string>
    <string name="educational_feed">рд╢реИрдХреНрд╖рд┐рдХ рдлреАрдб</string>
    <string name="custom_routine">рдХрд╕реНрдЯрдо рджрд┐рдирдЪрд░реНрдпрд╛</string>
    <string name="observation_diary">рдЕрд╡рд▓реЛрдХрди рдбрд╛рдпрд░реА</string>
    <string name="tina_chatbot">рдЯреАрдирд╛ (рдЪреИрдЯрдмреЙрдЯ)</string>
    <string name="tea_forum">ASD рдлреЛрд░рдо</string>
    
    <!-- Feed Page -->
    <string name="articles">рд▓реЗрдЦ</string>
    <string name="digital_library">рдбрд┐рдЬрд┐рдЯрд▓ рд▓рд╛рдЗрдмреНрд░реЗрд░реА</string>
    
    <!-- Forum -->
    <string name="new_post">рдирдИ рдкреЛрд╕реНрдЯ</string>
    <string name="publish">рдкреНрд░рдХрд╛рд╢рд┐рдд рдХрд░реЗрдВ</string>
    <string name="share_experience">ASD рдХреЗ рдмрд╛рд░реЗ рдореЗрдВ рдЕрдкрдирд╛ рдЕрдиреБрднрд╡, рдкреНрд░рд╢реНрди рдпрд╛ рд╕рд▓рд╛рд╣ рд╕рд╛рдЭрд╛ рдХрд░реЗрдВ...</string>
    <string name="write_something">рдкреНрд░рдХрд╛рд╢рд┐рдд рдХрд░рдиреЗ рд╕реЗ рдкрд╣рд▓реЗ рдХреБрдЫ рд▓рд┐рдЦреЗрдВ</string>
    <string name="confirm_publication">рдкреНрд░рдХрд╛рд╢рди рдХреА рдкреБрд╖реНрдЯрд┐ рдХрд░реЗрдВ</string>
    <string name="want_to_publish">рдХреНрдпрд╛ рдЖрдк рдЗрд╕ рдкреЛрд╕реНрдЯ рдХреЛ рдлреЛрд░рдо рдореЗрдВ рдкреНрд░рдХрд╛рд╢рд┐рдд рдХрд░рдирд╛ рдЪрд╛рд╣рддреЗ рд╣реИрдВ?</string>
    <string name="post_published">рдкреЛрд╕реНрдЯ рд╕рдлрд▓рддрд╛рдкреВрд░реНрд╡рдХ рдкреНрд░рдХрд╛рд╢рд┐рдд рд╣реБрдИ!</string>
    <string name="error_publishing">рдкреНрд░рдХрд╛рд╢рди рддреНрд░реБрдЯрд┐</string>
    
    <!-- Chatbot -->
    <string name="tina_assistant">рдЯреАрдирд╛ - ASD рд╕рд╣рд╛рдпрдХ</string>
    <string name="thinking">рд╕реЛрдЪ рд░рд╣рд╛ рд╣реИ...</string>
    <string name="type_message">рдЕрдкрдирд╛ рд╕рдВрджреЗрд╢ рдЯрд╛рдЗрдк рдХрд░реЗрдВ...</string>
    <string name="about_tina">ЁЯТЩ рдЯреАрдирд╛ рдХреЗ рдмрд╛рд░реЗ рдореЗрдВ</string>
    <string name="tina_intro">ЁЯдЦ **рдирдорд╕реНрддреЗ! рдореИрдВ рдЯреАрдирд╛ рд╣реВрдВ!**\n\nрдореИрдВ рдСрдЯрд┐рдЬреНрдо рдФрд░ рдиреНрдпреВрд░реЛрдбрд╛рдЗрд╡рд░реНрд╕рд┐рдЯреА рдореЗрдВ рд╡рд┐рд╢реЗрд╖рдЬреНрдЮрддрд╛ рд░рдЦрдиреЗ рд╡рд╛рд▓реА рд╡рд░реНрдЪреБрдЕрд▓ рдЕрд╕рд┐рд╕реНрдЯреЗрдВрдЯ рд╣реВрдВ, рдЬреЛ TISM рдХреЗ рд▓рд┐рдП рд╡рд┐рд╢реЗрд╖рдЬреНрдЮреЛрдВ рдХреА рдмрд╣реБрд╡рд┐рд╖рдпрдХ рдЯреАрдо рджреНрд╡рд╛рд░рд╛ рд╡рд┐рдХрд╕рд┐рдд рдХреА рдЧрдИ рд╣реИред</string>
    <string name="tina_specialization">ЁЯОп **рдореЗрд░реА рд╡рд┐рд╢реЗрд╖рдЬреНрдЮрддрд╛:**\nтАв ЁЯза рд╡рд┐рдХрд╛рд╕ рдФрд░ рд╡реНрдпрд╡рд╣рд╛рд░\nтАв ЁЯПл рд╕рдорд╛рд╡реЗрд╢реА рд╢рд┐рдХреНрд╖рд╛ рд░рдгрдиреАрддрд┐рдпрд╛рдВ\nтАв ЁЯТм рд╕рдВрдЪрд╛рд░ рдФрд░ рд╕рд╛рдорд╛рдЬрд┐рдХ рд╕рдВрдкрд░реНрдХ рддрдХрдиреАрдХреЗрдВ\nтАв ЁЯМН рдкрд░реНрдпрд╛рд╡рд░рдгреАрдп рдФрд░ рд╕рдВрд╡реЗрджреА рдЕрдиреБрдХреВрд▓рди\nтАв ЁЯЫая╕П рджреИрдирд┐рдХ рдЬреАрд╡рди рдХреЗ рд▓рд┐рдП рд╡реНрдпрд╛рд╡рд╣рд╛рд░рд┐рдХ рд╕рдВрд╕рд╛рдзрди</string>
    <string name="tina_scientific">ЁЯФм **рд╡реИрдЬреНрдЮрд╛рдирд┐рдХ рдЖрдзрд╛рд░:** рдореБрдЭреЗ рдиреНрдпреВрд░реЛрд▓реЙрдЬрд┐рд╕реНрдЯ, рдордиреЛрд╡реИрдЬреНрдЮрд╛рдирд┐рдХ, рд╡реНрдпрд╛рд╡рд╕рд╛рдпрд┐рдХ рдЪрд┐рдХрд┐рддреНрд╕рдХ, рднрд╛рд╖рд╛ рдЪрд┐рдХрд┐рддреНрд╕рдХ рдФрд░ рд╡рд┐рд╢реЗрд╖ рд╢рд┐рдХреНрд╖рдХреЛрдВ рджреНрд╡рд╛рд░рд╛ рд╕рддреНрдпрд╛рдкрд┐рдд рдЬреНрдЮрд╛рди рдХреЗ рд╕рд╛рде рдкреНрд░рд╢рд┐рдХреНрд╖рд┐рдд рдХрд┐рдпрд╛ рдЧрдпрд╛ рд╣реИред</string>
    <string name="tina_important">тЪая╕П **рдорд╣рддреНрд╡рдкреВрд░реНрдг:** рдореИрдВ рдирд┐рджрд╛рди рдирд╣реАрдВ рдХрд░рддреА рдФрд░ рд╕реНрд╡рд╛рд╕реНрдереНрдп рдкреЗрд╢реЗрд╡рд░реЛрдВ рдХрд╛ рд╡рд┐рдХрд▓реНрдк рдирд╣реАрдВ рд╣реВрдВред рдореЗрд░реА рднреВрдорд┐рдХрд╛ рдкреВрд░рдХ рд╣реИ, рд╕реВрдЪрдирд╛рддреНрдордХ рдФрд░ рд╡реНрдпрд╛рд╡рд╣рд╛рд░рд┐рдХ рд╕рд╣рд╛рдпрддрд╛ рдкреНрд░рджрд╛рди рдХрд░рдирд╛ред</string>
    <string name="tina_support">ЁЯТЩ **рдореИрдВ рд╡рд┐рд╢реНрд╡рд╕рдиреАрдп рдЬрд╛рдирдХрд╛рд░реА рдФрд░ рд╕рд╣рд╛рдиреБрднреВрддрд┐ рдХреЗ рд╕рд╛рде рдЖрдкрдХрд╛ рд╕рдорд░реНрдерди рдХрд░рдиреЗ рдХреЗ рд▓рд┐рдП рдпрд╣рд╛рдВ рд╣реВрдВ!**</string>
    <string name="understood_tina">рд╕рдордЭ рдЧрдпрд╛, рдЯреАрдирд╛! рдмрд╛рдд рдХрд░рддреЗ рд╣реИрдВ! ЁЯШК</string>
    <string name="tina_welcome">рдирдорд╕реНрддреЗ! рдореИрдВ TISM рдХреА рдСрдЯрд┐рдЬреНрдо рдФрд░ рдиреНрдпреВрд░реЛрдбрд╛рдЗрд╡рд░реНрд╕рд┐рдЯреА рд╡рд┐рд╢реЗрд╖рдЬреНрдЮ рд╡рд░реНрдЪреБрдЕрд▓ рдЕрд╕рд┐рд╕реНрдЯреЗрдВрдЯ рдЯреАрдирд╛ рд╣реВрдВ!\n\nрдореИрдВ рдирд┐рдореНрдирд▓рд┐рдЦрд┐рдд рдХреЗ рдмрд╛рд░реЗ рдореЗрдВ рд╡реИрдЬреНрдЮрд╛рдирд┐рдХ рд╕рд╛рдХреНрд╖реНрдп-рдЖрдзрд╛рд░рд┐рдд рд╡реНрдпрдХреНрддрд┐рдЧрдд рд╕рд╣рд╛рдпрддрд╛ рдФрд░ рдЬрд╛рдирдХрд╛рд░реА рдкреНрд░рджрд╛рди рдХрд░рдиреЗ рдХреЗ рд▓рд┐рдП рдпрд╣рд╛рдВ рд╣реВрдВ:\n\nтАв рд╡рд┐рдХрд╛рд╕ рдФрд░ рд╡реНрдпрд╡рд╣рд╛рд░\nтАв рд╕рдорд╛рд╡реЗрд╢реА рд╢рд┐рдХреНрд╖рд╛ рд░рдгрдиреАрддрд┐рдпрд╛рдВ\nтАв рд╕рдВрдЪрд╛рд░ рдФрд░ рд╕рд╛рдорд╛рдЬрд┐рдХ рд╕рдВрдкрд░реНрдХ рддрдХрдиреАрдХреЗрдВ\nтАв рдкрд░реНрдпрд╛рд╡рд░рдгреАрдп рдФрд░ рд╕рдВрд╡реЗрджреА рдЕрдиреБрдХреВрд▓рди\nтАв рджреИрдирд┐рдХ рдЬреАрд╡рди рдХреЗ рд▓рд┐рдП рд╡реНрдпрд╛рд╡рд╣рд╛рд░рд┐рдХ рд╕рдВрд╕рд╛рдзрди рдФрд░ рдЙрдкрдХрд░рдг\n\nрдореЗрд░рд╛ рдЬреНрдЮрд╛рди рдЖрдзрд╛рд░ рдиреНрдпреВрд░реЛрд▓реЙрдЬрд┐рд╕реНрдЯ, рдордиреЛрд╡реИрдЬреНрдЮрд╛рдирд┐рдХ, рд╡реНрдпрд╛рд╡рд╕рд╛рдпрд┐рдХ рдЪрд┐рдХрд┐рддреНрд╕рдХ, рднрд╛рд╖рд╛ рдЪрд┐рдХрд┐рддреНрд╕рдХ рдФрд░ рд╡рд┐рд╢реЗрд╖ рд╢рд┐рдХреНрд╖рдХреЛрдВ рд╕рд╣рд┐рдд рдмрд╣реБрд╡рд┐рд╖рдпрдХ рд╡рд┐рд╢реЗрд╖рдЬреНрдЮ рдЯреАрдо рджреНрд╡рд╛рд░рд╛ рд╡рд┐рдХрд╕рд┐рдд рдХрд┐рдпрд╛ рдЧрдпрд╛ рд╣реИред\n\nрдпрд╣ рдзреНрдпрд╛рди рд░рдЦрдирд╛ рдорд╣рддреНрд╡рдкреВрд░реНрдг рд╣реИ рдХрд┐ рдореИрдВ рдирд┐рджрд╛рди рдирд╣реАрдВ рдХрд░рддреА рдФрд░ рд╕реНрд╡рд╛рд╕реНрдереНрдп рдкреЗрд╢реЗрд╡рд░реЛрдВ рдХрд╛ рд╡рд┐рдХрд▓реНрдк рдирд╣реАрдВ рд╣реВрдВ - рдореЗрд░реА рднреВрдорд┐рдХрд╛ рдкреВрд░рдХ рд╣реИ, рдкрд░рд┐рд╡рд╛рд░реЛрдВ, рджреЗрдЦрднрд╛рд▓рдХрд░реНрддрд╛рдУрдВ рдФрд░ рдиреНрдпреВрд░реЛрдбрд╛рдЗрд╡рд░реНрдЬреЗрдВрдЯ рд╡реНрдпрдХреНрддрд┐рдпреЛрдВ рдХреЛ рд╡рд┐рд╢реНрд╡рд╕рдиреАрдп рдЬрд╛рдирдХрд╛рд░реА рдФрд░ рд╡реНрдпрд╛рд╡рд╣рд╛рд░рд┐рдХ рд╕рд╣рд╛рдпрддрд╛ рдкреНрд░рджрд╛рди рдХрд░рдирд╛ред\n\nрдЖрдЬ рдореИрдВ рдЖрдкрдХреА рдХреИрд╕реЗ рдорджрдж рдХрд░ рд╕рдХрддреА рд╣реВрдВ?</string>
    
    <!-- Diary -->
    <string name="diary_observations">рдЕрд╡рд▓реЛрдХрди рдбрд╛рдпрд░реА</string>
    <string name="no_observations">рдЕрднреА рддрдХ рдХреЛрдИ рдЕрд╡рд▓реЛрдХрди рдирд╣реАрдВ</string>
    <string name="tap_plus_start">рд╢реБрд░реВ рдХрд░рдиреЗ рдХреЗ рд▓рд┐рдП + рджрдмрд╛рдПрдВ</string>
    <string name="report_copied">рд░рд┐рдкреЛрд░реНрдЯ рдХреЙрдкреА рд╣реЛ рдЧрдИ! рдИрдореЗрд▓ рдпрд╛ WhatsApp рдореЗрдВ рдкреЗрд╕реНрдЯ рдХрд░реЗрдВ</string>
    <string name="progress">рдкреНрд░рдЧрддрд┐</string>
    <string name="behavior">рд╡реНрдпрд╡рд╣рд╛рд░</string>
    <string name="crisis">рд╕рдВрдХрдЯ</string>
    <string name="difficulty">рдХрдард┐рдирд╛рдИ</string>
    <string name="triggers">рдЯреНрд░рд┐рдЧрд░</string>
    
    <!-- Routine -->
    <string name="routine_of">%s рдХреА рджрд┐рдирдЪрд░реНрдпрд╛</string>
    <string name="support_level">%s рд╕рд╣рд╛рдпрддрд╛</string>
    <string name="filter_category">рд╢реНрд░реЗрдгреА рдХреЗ рдЕрдиреБрд╕рд╛рд░ рдлрд┐рд▓реНрдЯрд░ рдХрд░реЗрдВ:</string>
    <string name="completed">рдкреВрд░реНрдг</string>
    <string name="progress_count">рдкреНрд░рдЧрддрд┐: %d/%d</string>
    <string name="no_activities">рдХреЛрдИ рдЧрддрд┐рд╡рд┐рдзрд┐ рдирд╣реАрдВ рдорд┐рд▓реА</string>
    <string name="clear_filters">рдлрд┐рд▓реНрдЯрд░ рд╕рд╛рдл рдХрд░реЗрдВ</string>
    <string name="add_activity">рдЧрддрд┐рд╡рд┐рдзрд┐ рдЬреЛрдбрд╝реЗрдВ</string>
    <string name="edit_activity">рдЧрддрд┐рд╡рд┐рдзрд┐ рд╕рдВрдкрд╛рджрд┐рдд рдХрд░реЗрдВ</string>
    
    <!-- Categories -->
    <string name="morning">рд╕реБрдмрд╣</string>
    <string name="education">рд╢рд┐рдХреНрд╖рд╛</string>
    <string name="food">рднреЛрдЬрди</string>
    <string name="leisure">рдордиреЛрд░рдВрдЬрди</string>
    <string name="wellness">рдХрд▓реНрдпрд╛рдг</string>
    <string name="night">рд░рд╛рдд</string>
    <string name="all">рд╕рднреА</string>
    
    <!-- Profile Setup -->
    <string name="welcome">рд╕реНрд╡рд╛рдЧрдд рд╣реИ!</string>
    <string name="profile_setup_desc">рд╡реНрдпрдХреНрддрд┐рдЧрдд рджрд┐рдирдЪрд░реНрдпрд╛ рдмрдирд╛рдиреЗ рдХреЗ рд▓рд┐рдП, рдкрд╣рд▓реЗ рдмрдЪреНрдЪреЗ рдХреА рдкреНрд░реЛрдлрд╛рдЗрд▓ рд╕реЗрдЯ рдХрд░рддреЗ рд╣реИрдВред\n\nрдпрд╣ рд╣рдореЗрдВ рдЙрдореНрд░ рдХреЗ рдЕрдиреБрдХреВрд▓ рдЧрддрд┐рд╡рд┐рдзрд┐рдпрд╛рдВ рдФрд░ рд╕рд╣рд╛рдпрддрд╛ рд╕реНрддрд░ рд╕реБрдЭрд╛рдиреЗ рдореЗрдВ рдорджрдж рдХрд░рддрд╛ рд╣реИред</string>
    <string name="create_profile">рдкреНрд░реЛрдлрд╛рдЗрд▓ рдмрдирд╛рдПрдВ</string>
    <string name="edit_profile_menu">рдкреНрд░реЛрдлрд╛рдЗрд▓ рд╕рдВрдкрд╛рджрд┐рдд рдХрд░реЗрдВ</string>
    <string name="switch_child">рдмрдЪреНрдЪрд╛ рдмрджрд▓реЗрдВ</string>
    <string name="new_child">рдирдпрд╛ рдмрдЪреНрдЪрд╛</string>
    <string name="select_child">рдмрдЪреНрдЪрд╛ рдЪреБрдиреЗрдВ</string>
    
    <!-- Email Verification -->
    <string name="verify_email">рдИрдореЗрд▓ рд╕рддреНрдпрд╛рдкрд┐рдд рдХрд░реЗрдВ</string>
    <string name="verification_sent">рд╕рддреНрдпрд╛рдкрди рдИрдореЗрд▓ рднреЗрдЬрд╛ рдЧрдпрд╛!</string>
    <string name="check_email">рдЕрдкрдирд╛ рдЗрдирдмреЙрдХреНрд╕ рдЪреЗрдХ рдХрд░реЗрдВ</string>
    <string name="verification_desc">рд╣рдордиреЗ рдЖрдкрдХреЗ рдИрдореЗрд▓ рдкрд░ рд╕рддреНрдпрд╛рдкрди рд▓рд┐рдВрдХ рднреЗрдЬрд╛ рд╣реИред рдЕрдкрдирд╛ рдЦрд╛рддрд╛ рд╕рдХреНрд░рд┐рдп рдХрд░рдиреЗ рдХреЗ рд▓рд┐рдП рд▓рд┐рдВрдХ рдкрд░ рдХреНрд▓рд┐рдХ рдХрд░реЗрдВред</string>
    <string name="already_verified">рдкрд╣рд▓реЗ рд╕реЗ рд╕рддреНрдпрд╛рдкрд┐рдд - рд▓реЙрдЧрд┐рди рдХрд░реЗрдВ</string>
    <string name="resend_verification">рд╕рддреНрдпрд╛рдкрди рдИрдореЗрд▓ рдлрд┐рд░ рд╕реЗ рднреЗрдЬреЗрдВ</string>
    <string name="verifying">рд╕рддреНрдпрд╛рдкрд┐рдд рдХрд░ рд░рд╣реЗ рд╣реИрдВ...</string>
    
    <!-- Account Deletion -->
    <string name="delete_account">рдЦрд╛рддрд╛ рд╣рдЯрд╛рдПрдВ</string>
    <string name="delete_warning">рдпрд╣ рдХреНрд░рд┐рдпрд╛ рдЕрдкрд░рд┐рд╡рд░реНрддрдиреАрдп рд╣реИ!\n\nрдЖрдкрдХрд╛ рд╕рд╛рд░рд╛ рдбреЗрдЯрд╛ рд╕реНрдерд╛рдпреА рд░реВрдк рд╕реЗ рдЦреЛ рдЬрд╛рдПрдЧрд╛ред</string>
    <string name="delete_confirmation">рдкреБрд╖реНрдЯрд┐ рдХреЗ рд▓рд┐рдП, рдмрд┐рд▓реНрдХреБрд▓ рдЯрд╛рдЗрдк рдХрд░реЗрдВ:</string>
    <string name="delete_phrase">рдореЗрд░рд╛ рдЦрд╛рддрд╛ рд╣рдЯрд╛рдПрдВ</string>
    <string name="delete_input_hint">рдКрдкрд░ рдХрд╛ рд╡рд╛рдХреНрдп рдЯрд╛рдЗрдк рдХрд░реЗрдВ</string>
    <string name="delete_incorrect">рдЧрд▓рдд рд╡рд╛рдХреНрдпред рдмрдбрд╝реЗ-рдЫреЛрдЯреЗ рдЕрдХреНрд╖рд░ рдЪреЗрдХ рдХрд░реЗрдВред</string>
    <string name="confirm_password_delete">рдкрд╛рд╕рд╡рд░реНрдб рдХреА рдкреБрд╖реНрдЯрд┐ рдХрд░реЗрдВ</string>
    <string name="enter_password">рдЕрдкрдирд╛ рдкрд╛рд╕рд╡рд░реНрдб рджрд░реНрдЬ рдХрд░реЗрдВ</string>
    
    <!-- Common Actions -->
    <string name="save">рд╕реЗрд╡ рдХрд░реЗрдВ</string>
    <string name="cancel">рд░рджреНрдж рдХрд░реЗрдВ</string>
    <string name="confirm">рдкреБрд╖реНрдЯрд┐ рдХрд░реЗрдВ</string>
    <string name="delete">рд╣рдЯрд╛рдПрдВ</string>
    <string name="edit">рд╕рдВрдкрд╛рджрд┐рдд рдХрд░реЗрдВ</string>
    <string name="add">рдЬреЛрдбрд╝реЗрдВ</string>
    <string name="remove">рд╣рдЯрд╛рдПрдВ</string>
    <string name="update">рдЕрдкрдбреЗрдЯ рдХрд░реЗрдВ</string>
    <string name="close">рдмрдВрдж рдХрд░реЗрдВ</string>
    <string name="ok">рдареАрдХ рд╣реИ</string>
    <string name="yes">рд╣рд╛рдВ</string>
    <string name="no">рдирд╣реАрдВ</string>
    <string name="share">рд╕рд╛рдЭрд╛ рдХрд░реЗрдВ</string>
    
    <!-- Messages -->
    <string name="success">рд╕рдлрд▓</string>
    <string name="error">рддреНрд░реБрдЯрд┐</string>
    <string name="loading">рд▓реЛрдб рд╣реЛ рд░рд╣рд╛ рд╣реИ...</string>
    <string name="connection_error">рдХрдиреЗрдХреНрд╢рди рддреНрд░реБрдЯрд┐</string>
    <string name="try_again">рдлрд┐рд░ рдХреЛрд╢рд┐рд╢ рдХрд░реЗрдВ</string>
    <string name="updated_successfully">рд╕рдлрд▓рддрд╛рдкреВрд░реНрд╡рдХ рдЕрдкрдбреЗрдЯ рд╣реБрдЖ!</string>
    <string name="deleted_successfully">рд╕рдлрд▓рддрд╛рдкреВрд░реНрд╡рдХ рд╣рдЯрд╛рдпрд╛ рдЧрдпрд╛</string>
    <string name="saved_successfully">рд╕рдлрд▓рддрд╛рдкреВрд░реНрд╡рдХ рд╕реЗрд╡ рд╣реБрдЖ!</string>
    <string name="welcome_message">рдирдорд╕реНрддреЗ, рд╕реНрд╡рд╛рдЧрдд рд╣реИ!</string>
    <string name="no_account">рдХреЛрдИ рдЦрд╛рддрд╛ рдирд╣реАрдВ рд╣реИ? рд░рдЬрд┐рд╕реНрдЯрд░ рдХрд░реЗрдВ</string>
    <string name="fill_all_fields">рд╕рднреА рдлреАрд▓реНрдб рднрд░реЗрдВ</string>
    <string name="login_error">рд▓реЙрдЧрд┐рди рддреНрд░реБрдЯрд┐</string>
    <string name="connection_error_detail">рдХрдиреЗрдХреНрд╢рди рддреНрд░реБрдЯрд┐: %s</string>
    
    <!-- Validation -->
    <string name="field_required">рдпрд╣ рдлреАрд▓реНрдб рдЖрд╡рд╢реНрдпрдХ рд╣реИ</string>
    <string name="invalid_email">рдЕрдорд╛рдиреНрдп рдИрдореЗрд▓</string>
    <string name="password_too_short">рдкрд╛рд╕рд╡рд░реНрдб рдХрдо рд╕реЗ рдХрдо 8 рдЕрдХреНрд╖рд░ рдХрд╛ рд╣реЛрдирд╛ рдЪрд╛рд╣рд┐рдП</string>
    <string name="passwords_dont_match">рдкрд╛рд╕рд╡рд░реНрдб рдореЗрд▓ рдирд╣реАрдВ рдЦрд╛рддреЗ</string>
    <string name="username_invalid">рдпреВрдЬрд░рдиреЗрдо рдореЗрдВ рдХреЗрд╡рд▓ рдЫреЛрдЯреЗ рдЕрдХреНрд╖рд░, рд╕рдВрдЦреНрдпрд╛ рдФрд░ _ рд╣реЛ рд╕рдХрддреЗ рд╣реИрдВ</string>
    
    <!-- Cooldowns -->
    <string name="name_cooldown">рдирд╛рдо рджрд┐рди рдореЗрдВ рдХреЗрд╡рд▓ рдПрдХ рдмрд╛рд░ рдмрджрд▓рд╛ рдЬрд╛ рд╕рдХрддрд╛ рд╣реИ</string>
    <string name="username_cooldown">рдпреВрдЬрд░рдиреЗрдо 3 рджрд┐рди рдореЗрдВ рдПрдХ рдмрд╛рд░ рдмрджрд▓рд╛ рдЬрд╛ рд╕рдХрддрд╛ рд╣реИ</string>
    <string name="user_type_cooldown">рдЙрдкрдпреЛрдЧрдХрд░реНрддрд╛ рдкреНрд░рдХрд╛рд░ рджрд┐рди рдореЗрдВ рдХреЗрд╡рд▓ рдПрдХ рдмрд╛рд░ рдмрджрд▓рд╛ рдЬрд╛ рд╕рдХрддрд╛ рд╣реИ</string>
    
    <!-- Activities -->
    <string name="wake_up">рдЬрд╛рдЧрдирд╛</string>
    <string name="wake_up_desc">рдордзреБрд░ рд╕рдВрдЧреАрдд рдХреЗ рд╕рд╛рде рдЬрд╛рдЧрдирд╛</string>
    <string name="brush_teeth">рджрд╛рдВрдд рд╕рд╛рдл рдХрд░рдирд╛</string>
    <string name="brush_teeth_desc">рдореБрд▓рд╛рдпрдо рдмреНрд░рд╢ рд╕реЗ 2 рдорд┐рдирдЯ</string>
    <string name="breakfast">рдирд╛рд╢реНрддрд╛</string>
    <string name="breakfast_desc">рдореЗрдЬ рдкрд░ рдмреИрдардХрд░ рдЦрд╛рдирд╛</string>
    <string name="educational_activity">рд╢реИрдХреНрд╖рд┐рдХ рдЧрддрд┐рд╡рд┐рдзрд┐</string>
    <string name="educational_activity_desc">рд╢реИрдХреНрд╖рд┐рдХ рдЦреЗрд▓ рдпрд╛ рд╕реНрдХреВрд▓</string>
    <string name="snack">рдирд╛рд╢реНрддрд╛</string>
    <string name="snack_desc">рдлрд▓ рдпрд╛ рд╕реНрд╡рд╕реНрде рдирд╛рд╢реНрддрд╛</string>
    <string name="music">рд╕рдВрдЧреАрдд</string>
    <string name="music_desc">рд╕рдВрдЧреАрдд рд╕реБрдирдирд╛ рдпрд╛ рдмрдЬрд╛рдирд╛</string>
    <string name="draw">рдЪрд┐рддреНрд░ рдмрдирд╛рдирд╛</string>
    <string name="draw_desc">рд╕реНрд╡рддрдВрддреНрд░ рдЪрд┐рддреНрд░рдХрд╛рд░реА рдЧрддрд┐рд╡рд┐рдзрд┐</string>
    <string name="numbers">рд╕рдВрдЦреНрдпрд╛рдПрдВ</string>
    <string name="numbers_desc">рд╕рдВрдЦреНрдпрд╛ рдХреЗ рдЦреЗрд▓</string>
    <string name="sensory_break">рд╕рдВрд╡реЗрджреА рд╡рд┐рд░рд╛рдо</string>
    <string name="sensory_break_desc">рд╢рд╛рдВрддрд┐ рдФрд░ рд╕реНрд╡-рдирд┐рдпрдВрддреНрд░рдг рдХрд╛ рд╕рдордп</string>
    <string name="dinner">рд░рд╛рдд рдХрд╛ рдЦрд╛рдирд╛</string>
    <string name="dinner_desc">рдкрд░рд┐рд╡рд╛рд░ рдХреЗ рд╕рд╛рде рднреЛрдЬрди</string>
    <string name="bath">рд╕реНрдирд╛рди</string>
    <string name="bath_desc">рдЧреБрдирдЧреБрдирд╛ рдкрд╛рдиреА, рдореБрд▓рд╛рдпрдо рд╕реНрдкрдВрдЬ</string>
    <string name="sleep">рд╕реЛрдирд╛</string>
    <string name="sleep_desc">рд╕реЛрдиреЗ рдХреЗ рд▓рд┐рдП рдордзреБрд░ рд╕рдВрдЧреАрдд</string>
    
    <!-- Forum Specific -->
    <string name="welcome_forum">ASD рдлреЛрд░рдо рдореЗрдВ рдЖрдкрдХрд╛ рд╕реНрд╡рд╛рдЧрдд рд╣реИ! ЁЯТЩ</string>
    <string name="first_post_message">рдЕрдиреБрднрд╡ рд╕рд╛рдЭрд╛ рдХрд░рдиреЗ рдпрд╛\nрд╕рдореБрджрд╛рдп рд╕реЗ рдкреНрд░рд╢реНрди рдкреВрдЫрдиреЗ рд╡рд╛рд▓реЗ рдкрд╣рд▓реЗ рд╡реНрдпрдХреНрддрд┐ рдмрдиреЗрдВ</string>
    <string name="create_first_post">рдкрд╣рд▓реА рдкреЛрд╕реНрдЯ рдмрдирд╛рдПрдВ</string>
    <string name="delete_post">рдкреЛрд╕реНрдЯ рд╣рдЯрд╛рдПрдВ</string>
    <string name="delete_post_confirm">рдХреНрдпрд╛ рдЖрдк рдЗрд╕ рдкреЛрд╕реНрдЯ рдХреЛ рд╣рдЯрд╛рдирд╛ рдЪрд╛рд╣рддреЗ рд╣реИрдВ? рдпрд╣ рдХреНрд░рд┐рдпрд╛ рдкреВрд░реНрд╡рд╡рдд рдирд╣реАрдВ рдХреА рдЬрд╛ рд╕рдХрддреАред</string>
    <string name="post_deleted_success">рдкреЛрд╕реНрдЯ рд╕рдлрд▓рддрд╛рдкреВрд░реНрд╡рдХ рд╣рдЯрд╛рдИ рдЧрдИ</string>
    <string name="error_deleting_post">рдкреЛрд╕реНрдЯ рд╣рдЯрд╛рдиреЗ рдореЗрдВ рддреНрд░реБрдЯрд┐: %s</string>
    <string name="report_post">рд░рд┐рдкреЛрд░реНрдЯ рдХрд░реЗрдВ</string>
    <string name="report_post_title">рдкреЛрд╕реНрдЯ рд░рд┐рдкреЛрд░реНрдЯ рдХрд░реЗрдВ</string>
    <string name="report_post_confirm">рдХреНрдпрд╛ рдЖрдк рдЗрд╕ рдкреЛрд╕реНрдЯ рдХреЛ рд░рд┐рдкреЛрд░реНрдЯ рдХрд░рдирд╛ рдЪрд╛рд╣рддреЗ рд╣реИрдВ?</string>
    <string name="post_reported">рдкреЛрд╕реНрдЯ рд░рд┐рдкреЛрд░реНрдЯ рдХреА рдЧрдИ</string>
    <string name="now">рдЕрднреА</string>
    
    <!-- Search -->
    <string name="search_posts">рдкреЛрд╕реНрдЯ, рд▓реЛрдЧ рдпрд╛ рд╡рд┐рд╖рдп рдЦреЛрдЬреЗрдВ...</string>
    <string name="no_results_found">рдХреЛрдИ рдкрд░рд┐рдгрд╛рдо рдирд╣реАрдВ рдорд┐рд▓рд╛</string>
    <string name="try_different_keywords">рдЕрд▓рдЧ рдХреАрд╡рд░реНрдб рдЖрдЬрд╝рдорд╛рдПрдВ рдпрд╛\nрдиреАрдЪреЗ рдХреА рд╢реНрд░реЗрдгрд┐рдпреЛрдВ рдХреЛ рджреЗрдЦреЗрдВ</string>
    <string name="type_to_search">рдЦреЛрдЬрдиреЗ рдХреЗ рд▓рд┐рдП рдЯрд╛рдЗрдк рдХрд░реЗрдВ...</string>
    <string name="find_posts_profiles">ASD рд╕рдореБрджрд╛рдп рдореЗрдВ рдкреЛрд╕реНрдЯ, рдкреНрд░реЛрдлрд╛рдЗрд▓ рдФрд░\nрд╣реИрд╢рдЯреИрдЧ рдЦреЛрдЬреЗрдВ</string>
    <string name="popular_categories">рд▓реЛрдХрдкреНрд░рд┐рдп рд╢реНрд░реЗрдгрд┐рдпрд╛рдВ</string>
    <string name="recent_searches">рд╣рд╛рд▓ рдХреА рдЦреЛрдЬреЗрдВ</string>
    <string name="searches_appear_here">рдЖрдкрдХреА рдЦреЛрдЬреЗрдВ рдпрд╣рд╛рдВ рджрд┐рдЦрд╛рдИ рджреЗрдВрдЧреА</string>
    <string name="general">рд╕рд╛рдорд╛рдиреНрдп</string>
    <string name="tips">рд╕реБрдЭрд╛рд╡</string>
    <string name="experiences">рдЕрдиреБрднрд╡</string>
    <string name="questions">рдкреНрд░рд╢реНрди</string>
    <string name="resources">рд╕рдВрд╕рд╛рдзрди</string>
    
    <!-- Chatbot Suggestions -->
    <string name="how_identify_autism">рдСрдЯрд┐рдЬреНрдо рдХреА рдкрд╣рдЪрд╛рди рдХреИрд╕реЗ рдХрд░реЗрдВ?</string>
    <string name="child_not_speaking">рдореЗрд░рд╛ рдмрдЪреНрдЪрд╛ рдирд╣реАрдВ рдмреЛрд▓рддрд╛, рдХреНрдпрд╛ рдпрд╣ рдСрдЯрд┐рдЬреНрдо рд╣реИ?</string>
    <string name="what_therapies_work">рдХреМрди рд╕реА рдЪрд┐рдХрд┐рддреНрд╕рд╛ рдХрд╛рдо рдХрд░рддреА рд╣реИ?</string>
    <string name="help_at_school">рд╕реНрдХреВрд▓ рдореЗрдВ рдХреИрд╕реЗ рдорджрдж рдХрд░реЗрдВ?</string>
    <string name="autism_rights">рдСрдЯрд┐рдЬреНрдо рдЕрдзрд┐рдХрд╛рд░</string>
    <string name="child_tantrums">рдмрдЪреНрдЪреЗ рдХреЗ рдЧреБрд╕реНрд╕реЗ рдХреЗ рджреМрд░реЗ</string>
    
    <!-- Diary -->
    <string name="new_observation">рдирдпрд╛ рдЕрд╡рд▓реЛрдХрди</string>
    <string name="edit_observation">рдЕрд╡рд▓реЛрдХрди рд╕рдВрдкрд╛рджрд┐рдд рдХрд░реЗрдВ</string>
    <string name="observation_type">рдкреНрд░рдХрд╛рд░:</string>
    <string name="title">рд╢реАрд░реНрд╖рдХ</string>
    <string name="detailed_description">рд╡рд┐рд╕реНрддреГрдд рд╡рд┐рд╡рд░рдг</string>
    <string name="intensity">рддреАрд╡реНрд░рддрд╛: %d</string>
    <string name="observer">рдЕрд╡рд▓реЛрдХрдирдХрд░реНрддрд╛:</string>
    <string name="possible_triggers">рд╕рдВрднрд╛рд╡рд┐рдд рдЯреНрд░рд┐рдЧрд░:</string>
    <string name="delete_observation">рдЕрд╡рд▓реЛрдХрди рд╣рдЯрд╛рдПрдВ</string>
    <string name="delete_observation_confirm">рдХреНрдпрд╛ рдЖрдк рдЗрд╕ рдЕрд╡рд▓реЛрдХрди рдХреЛ рд╣рдЯрд╛рдирд╛ рдЪрд╛рд╣рддреЗ рд╣реИрдВ?</string>
    <string name="observation_title_empty">рдЕрд╡рд▓реЛрдХрди рд╢реАрд░реНрд╖рдХ рдЦрд╛рд▓реА рдирд╣реАрдВ рд╣реЛ рд╕рдХрддрд╛</string>
    
    <!-- Profile -->
    <string name="not_defined">рдкрд░рд┐рднрд╛рд╖рд┐рдд рдирд╣реАрдВ</string>
    <string name="confirm_change">рдкрд░рд┐рд╡рд░реНрддрди рдХреА рдкреБрд╖реНрдЯрд┐ рдХрд░реЗрдВ</string>
    <string name="change_name_to">рдирд╛рдо рдХреЛ "%s" рдореЗрдВ рдмрджрд▓реЗрдВ?</string>
    <string name="change_username_to">рдпреВрдЬрд░рдиреЗрдо рдХреЛ @%s рд╕реЗ @%s рдореЗрдВ рдмрджрд▓реЗрдВ?</string>
    <string name="error_updating_name">рдирд╛рдо рдЕрдкрдбреЗрдЯ рдХрд░рдиреЗ рдореЗрдВ рддреНрд░реБрдЯрд┐</string>
    <string name="error_updating_username">рдпреВрдЬрд░рдиреЗрдо рдЕрдкрдбреЗрдЯ рдХрд░рдиреЗ рдореЗрдВ рддреНрд░реБрдЯрд┐</string>
    <string name="error_updating_type">рдкреНрд░рдХрд╛рд░ рдЕрдкрдбреЗрдЯ рдХрд░рдиреЗ рдореЗрдВ рддреНрд░реБрдЯрд┐</string>
    <string name="username_help">рдХреЗрд╡рд▓ рдЫреЛрдЯреЗ рдЕрдХреНрд╖рд░, рд╕рдВрдЦреНрдпрд╛ рдФрд░ _</string>
    <string name="username_cooldown_info">рдпреВрдЬрд░рдиреЗрдо 3 рджрд┐рди рдореЗрдВ рдПрдХ рдмрд╛рд░ рдмрджрд▓рд╛ рдЬрд╛ рд╕рдХрддрд╛ рд╣реИ</string>
    <string name="confirm_password_title">рдкрд╛рд╕рд╡рд░реНрдб рдХреА рдкреБрд╖реНрдЯрд┐ рдХрд░реЗрдВ</string>
    <string name="error_deleting_account">рдЦрд╛рддрд╛ рд╣рдЯрд╛рдиреЗ рдореЗрдВ рддреНрд░реБрдЯрд┐</string>
    
    <!-- Additional strings -->
    <string name="type_updated">рдкреНрд░рдХрд╛рд░ рдЕрдкрдбреЗрдЯ рд╣реБрдЖ!</string>
    <string name="name_updated">рдирд╛рдо рдЕрдкрдбреЗрдЯ рд╣реБрдЖ!</string>
    <string name="username_updated">рдпреВрдЬрд░рдиреЗрдо рдЕрдкрдбреЗрдЯ рд╣реБрдЖ!</string>
    <string name="account_deleted">рдЦрд╛рддрд╛ рд╕рдлрд▓рддрд╛рдкреВрд░реНрд╡рдХ рд╣рдЯрд╛рдпрд╛ рдЧрдпрд╛</string>
    <string name="incorrect_password">рдЧрд▓рдд рдкрд╛рд╕рд╡рд░реНрдб</string>
    <string name="user_not_found">рдЙрдкрдпреЛрдЧрдХрд░реНрддрд╛ рдирд╣реАрдВ рдорд┐рд▓рд╛</string>
    <string name="email_not_verified">рдИрдореЗрд▓ рдЕрднреА рддрдХ рд╕рддреНрдпрд╛рдкрд┐рдд рдирд╣реАрдВ рд╣реИ</string>
    <string name="verification_email_sent">рд╕рддреНрдпрд╛рдкрди рдИрдореЗрд▓ рдлрд┐рд░ рд╕реЗ рднреЗрдЬрд╛ рдЧрдпрд╛!</string>
    <string name="checking_verification">рдЬрд╛рдВрдЪ рд░рд╣реЗ рд╣реИрдВ...</string>
    <string name="already_have_account">рдкрд╣рд▓реЗ рд╕реЗ рдЦрд╛рддрд╛ рд╣реИ? рд▓реЙрдЧрд┐рди рдХрд░реЗрдВ</string>
    <string name="create_account">рдЦрд╛рддрд╛ рдмрдирд╛рдПрдВ</string>
    <string name="account_created">рдЦрд╛рддрд╛ рдмрдирд╛рдпрд╛ рдЧрдпрд╛! рд╕рдХреНрд░рд┐рдпрдг рдХреЗ рд▓рд┐рдП рдИрдореЗрд▓ рдЪреЗрдХ рдХрд░реЗрдВ</string>
    <string name="example123">рдЙрджрд╛рд╣рд░рдг123</string>
</resources>